pinyinsplit.py
pinyinsplit-0.1.4.dist-info/LICENSE.txt
pinyinsplit-0.1.4.dist-info/METADATA
pinyinsplit-0.1.4.dist-info/WHEEL
pinyinsplit-0.1.4.dist-info/top_level.txt
pinyinsplit-0.1.4.dist-info/RECORD
