Metadata-Version: 2.1
Name: pinyinsplit
Version: 0.1.4
Summary: A Python library to split a Chinese Pinyin phrase into possible permutations of Chinese Pinyin words
Home-page: https://github.com/throput/pinyinsplit
Author: Thomas Lee
Author-email: thomaslee@throput.com
License: MIT
Keywords: chinese pinyin
Platform: UNKNOWN
Classifier: Development Status :: 3 - Alpha
Classifier: License :: OSI Approved :: MIT License
Classifier: Programming Language :: Python :: 3.6
Classifier: Topic :: Text Processing :: Linguistic
Requires-Dist: pygtrie (>=2.3)
